django_includecontents-4.0.1.dist-info/METADATA
django_includecontents-4.0.1.dist-info/WHEEL
django_includecontents-4.0.1.dist-info/entry_points.txt
includecontents/__init__.py
includecontents/django/__init__.py
includecontents/django/base.py
includecontents/django/engine.py
includecontents/django/loaders.py
includecontents/icons/__init__.py
includecontents/icons/builder.py
includecontents/icons/cache.py
includecontents/icons/definitions.py
includecontents/icons/exceptions.py
includecontents/icons/finders.py
includecontents/icons/html.py
includecontents/icons/symbols.py
includecontents/icons/templatetags/__init__.py
includecontents/icons/templatetags/icons.py
includecontents/icons/utils.py
includecontents/icons/validation.py
includecontents/jinja2/__init__.py
includecontents/jinja2/attrs.py
includecontents/jinja2/context.py
includecontents/jinja2/extension.py
includecontents/jinja2/preprocess.py
includecontents/jinja2/props.py
includecontents/next_version.py
includecontents/shared/__init__.py
includecontents/shared/attrs.py
includecontents/shared/context.py
includecontents/shared/enums.py
includecontents/shared/props.py
includecontents/templatetags/__init__.py
includecontents/templatetags/includecontents.py
django_includecontents-4.0.1.dist-info/RECORD
