Metadata-Version: 2.1
Name: django-includecontents
Version: 4.0.1
Summary: Django includecontents component-like tag
Author-Email: Chris Beaven <smileychris@gmail.com>
License: MIT
Classifier: Development Status :: 4 - Beta
Classifier: Environment :: Web Environment
Classifier: Intended Audience :: Developers
Classifier: License :: OSI Approved :: MIT License
Classifier: Framework :: Django
Classifier: Framework :: Django :: 4
Classifier: Framework :: Django :: 5
Classifier: Programming Language :: Python :: 3
Classifier: Topic :: Software Development :: Libraries :: Python Modules
Project-URL: Repository, https://github.com/SmileyChris/django-includecontents
Project-URL: Documentation, https://smileychris.github.io/django-includecontents/
Requires-Python: >=3.8
Requires-Dist: django
Requires-Dist: packaging
Provides-Extra: test
Requires-Dist: pytest; extra == "test"
Requires-Dist: pytest-django; extra == "test"
Requires-Dist: pytest-mock; extra == "test"
Provides-Extra: deploy
Requires-Dist: pdm; extra == "deploy"
Requires-Dist: pdm.backend; extra == "deploy"
Provides-Extra: docs
Requires-Dist: mkdocs>=1.5.0; extra == "docs"
Requires-Dist: mkdocs-material>=9.0.0; extra == "docs"
Requires-Dist: mkdocstrings[python]>=0.20.0; extra == "docs"
Requires-Dist: pymdown-extensions>=9.0.0; extra == "docs"
Requires-Dist: mike>=2.0.0; extra == "docs"
Provides-Extra: jinja
Requires-Dist: jinja2>=3.1; extra == "jinja"
